Main/__init__.py
Main/check_layout_model.py
Main/config.py
Main/convert.py
Main/herbarium_ocr.py
Main/image_processer.py
Main/layout_models/doclayout_yolo_docstructbench_imgsz1024.pt
herbarium_ocr-0.2.0.dist-info/licenses/LICENSE
ocr_clients/__init__.py
ocr_clients/openai_client.py
ocr_clients/surya_ocr_client.py
ocr_clients/xfyun_http_ocr_client.py
output_generators/__init__.py
output_generators/html_generator.py
output_generators/json_generator.py
output_generators/markdown_generator.py
output_generators/xml_generator.py
herbarium_ocr-0.2.0.dist-info/METADATA
herbarium_ocr-0.2.0.dist-info/WHEEL
herbarium_ocr-0.2.0.dist-info/entry_points.txt
herbarium_ocr-0.2.0.dist-info/top_level.txt
herbarium_ocr-0.2.0.dist-info/RECORD
