Metadata-Version: 2.4
Name: herbarium-ocr
Version: 0.2.0
Summary: OCR tool for botanical documents using layout analysis and LLMs/OCR engines.
Author-email: Esen Zhou <zhouyixin231@mails.ucas.ac.cn>
License:                     GNU AFFERO GENERAL PUBLIC LICENSE
Project-URL: Homepage, https://gitee.com/esenzhou/Herbarium-OCR-Public
Project-URL: Bug Tracker, https://gitee.com/esenzhou/Herbarium-OCR-Public/issues
Keywords: ocr,botany,llm,document analysis
Classifier: Development Status :: 3 - Alpha
Classifier: Intended Audience :: Science/Research
Classifier: Intended Audience :: Developers
Classifier: License :: OSI Approved :: GNU Affero General Public License v3 or later (AGPLv3+)
Classifier: Operating System :: OS Independent
Classifier: Programming Language :: Python :: 3
Classifier: Programming Language :: Python :: 3.10
Classifier: Programming Language :: Python :: 3.11
Classifier: Programming Language :: Python :: 3.12
Classifier: Topic :: Scientific/Engineering :: Image Recognition
Classifier: Topic :: Text Processing :: General
Classifier: Topic :: Utilities
Requires-Python: >=3.10
License-File: LICENSE
Requires-Dist: opencv-python-headless>=4.11.0.86
Requires-Dist: Pillow>=10.4.0
Requires-Dist: numpy>=2.2.5
Requires-Dist: tqdm>=4.67.0
Requires-Dist: PyMuPDF>=1.25.5
Requires-Dist: requests>=2.20.0
Requires-Dist: openai>=1.75.0
Requires-Dist: doclayout_yolo==0.0.3
Requires-Dist: huggingface_hub>=0.30.2
Requires-Dist: toml>=0.10.2
Provides-Extra: full
Requires-Dist: pytesseract>=0.3.10; extra == "full"
Requires-Dist: requests>=2.20.0; extra == "full"
Requires-Dist: surya-ocr>=0.13.1; extra == "full"
Provides-Extra: dev
Requires-Dist: pytest; extra == "dev"
Requires-Dist: flake8; extra == "dev"
Requires-Dist: black; extra == "dev"
Dynamic: license-file
